ultrabase64/__init__.py
ultrabase64/ultrabase64.cpython-314-darwin.so
ultrabase64-1.1.0.dist-info/METADATA
ultrabase64-1.1.0.dist-info/WHEEL
ultrabase64-1.1.0.dist-info/licenses/LICENSE
ultrabase64-1.1.0.dist-info/RECORD
