Metadata-Version: 2.4
Name: ultrabase64
Version: 1.1.0
Classifier: Development Status :: 4 - Beta
Classifier: Intended Audience :: Developers
Classifier: License :: OSI Approved :: MIT License
Classifier: License :: OSI Approved :: Apache Software License
Classifier: Operating System :: OS Independent
Classifier: Programming Language :: Python :: 3
Classifier: Programming Language :: Python :: 3.8
Classifier: Programming Language :: Python :: 3.9
Classifier: Programming Language :: Python :: 3.10
Classifier: Programming Language :: Python :: 3.11
Classifier: Programming Language :: Python :: 3.12
Classifier: Programming Language :: Rust
Classifier: Topic :: Software Development :: Libraries :: Python Modules
Classifier: Topic :: Text Processing
License-File: LICENSE
Summary: Ultra-fast Base64 encoding/decoding library with SIMD and multithreading support
Keywords: base64,encoding,simd,multithreading,performance
Home-Page: https://github.com/ruslano69/ultrabase64
Author-email: Your Name <your.email@example.com>
License: MIT OR Apache-2.0
Requires-Python: >=3.8
Project-URL: Homepage, https://github.com/yourusername/ultrabase64
Project-URL: Issues, https://github.com/yourusername/ultrabase64/issues
Project-URL: Repository, https://github.com/yourusername/ultrabase64
